wireviz_web/__init__.py
wireviz_web/cli.py
wireviz_web/core.py
wireviz_web/plantuml.py
wireviz_web/server.py
wireviz_web/util.py
wireviz_web-0.4.2.dist-info/LICENSE
wireviz_web-0.4.2.dist-info/METADATA
wireviz_web-0.4.2.dist-info/WHEEL
wireviz_web-0.4.2.dist-info/entry_points.txt
wireviz_web-0.4.2.dist-info/RECORD
