Metadata-Version: 2.3
Name: wireviz-web
Version: 0.4.2
Summary: A wrapper around WireViz for bringing it to the web. Easily document cables and wiring harnesses.
License: AGPLv3
Keywords: cable,connector,connector-editor,hardware,harness,wiring,wiring-diagram,wiring-harness
Author: Jürgen Key
Author-email: jkey@arcor.de
Requires-Python: >=3.8
Classifier: Development Status :: 4 - Beta
Classifier: Environment :: Console
Classifier: Intended Audience :: Developers
Classifier: Intended Audience :: Education
Classifier: Intended Audience :: Information Technology
Classifier: Intended Audience :: Science/Research
Classifier: Intended Audience :: System Administrators
Classifier: License :: OSI Approved :: GNU Affero General Public License v3
Classifier: License :: Other/Proprietary License
Classifier: Operating System :: MacOS
Classifier: Operating System :: POSIX
Classifier: Operating System :: Unix
Classifier: Programming Language :: Python
Classifier: Programming Language :: Python :: 3
Classifier: Programming Language :: Python :: 3.8
Classifier: Programming Language :: Python :: 3.9
Classifier: Programming Language :: Python :: 3.10
Classifier: Programming Language :: Python :: 3.11
Classifier: Programming Language :: Python :: 3.12
Classifier: Programming Language :: Python :: 3.13
Classifier: Topic :: Communications
Classifier: Topic :: Internet
Classifier: Topic :: Internet :: WWW/HTTP
Classifier: Topic :: Scientific/Engineering :: Human Machine Interfaces
Classifier: Topic :: Scientific/Engineering :: Information Analysis
Classifier: Topic :: Scientific/Engineering :: Interface Engine/Protocol Translator
Classifier: Topic :: Scientific/Engineering :: Visualization
Classifier: Topic :: Software Development :: Libraries
Classifier: Topic :: Text Processing
Classifier: Topic :: Utilities
Requires-Dist: Flask-Cors (<6)
Requires-Dist: click (<9)
Requires-Dist: flask (<2.3)
Requires-Dist: flask-restx (<1.4)
Requires-Dist: importlib_metadata (>=3.3,<7) ; python_version < "3.8"
Requires-Dist: pillow (>=9,<12)
Requires-Dist: werkzeug (<4)
Requires-Dist: wireviz (==0.4.1)
Project-URL: Homepage, https://community.hiveeyes.org/t/bringing-wireviz-to-the-web/3700
Project-URL: Issues, https://github.com/daq-tools/wireviz-web/issues
Project-URL: Repository, https://github.com/daq-tools/wireviz-web
